Workbook

Sheet Cover
C4: 3-Statement Modeling | K4: Developed By : Priyam Chandan
C7: Table of Contents | K7: Model Checks
C9: Output!A1 | K9: Model Exceeding Operational Capacity? | N9: 0
C10: Inputs!A1 | K10: Unused Tax Losses Remaining? | N10: 0
C11: Model!A1 | K11: Balance Sheet Unbalanced? | N11: 0
K12: Blue Colour | N12: Hard Code
K13: Black Colour | N13: Forumlas

Sheet Output
B3: Dashboard: Charts & Graphs
B5: All figures in USD thousands unless stated | H5: 2020 | I5: 2021 | J5: 2022 | K5: 2023 | L5: 2024 | M5: 2025 | N5: 2026 | O5: 2027
B7: Driver Switch | E7: =Inputs!E7 -> 2
C9: INCOME STATEMENT
C11: Revenue | H11: =Model!F11 -> 50589 | I11: =Model!G11 -> 51647.865 | J11: =Model!H11 -> 53760.85 | K11: =Model!I11 -> 56481.149 | L11: =Model!J11 -> 57616.42 | M11: =Model!K11 -> 58774.51 | N11: =Model!L11 -> 59659.067 | O11: =Model!M11 -> 60257.149
C13: EBITDA | H13: =Model!F18 -> 18403.7 | I13: =Model!G18 -> 18606.851 | J13: =Model!H18 -> 19811.448 | K13: =Model!I18 -> 21227.155 | L13: =Model!J18 -> 21243.681 | M13: =Model!K18 -> 21247 | N13: =Model!L18 -> 21160.454 | O13: =Model!M18 -> 20762.164
C14: EBITDA Margin | H14: =H13/H11 -> 0.36378857 | I14: =I13/I11 -> 0.36026369 | J14: =J13/J11 -> 0.3685107 | K14: =K13/K11 -> 0.37582726 | L14: =L13/L11 -> 0.3687088 | M14: =M13/M11 -> 0.36150025 | N14: =N13/N11 -> 0.35468966 | O14: =O13/O11 -> 0.34455935
C16: Net Income | H16: =Model!F35 -> 10800.7 | I16: =Model!G35 -> 10529.851 | J16: =Model!H35 -> 11190.449 | K16: =Model!I35 -> 10196.115 | L16: =Model!J35 -> 9750.2162 | M16: =Model!K35 -> 9762.7041 | N16: =Model!L35 -> 9700.4464 | O16: =Model!M35 -> 9358.5488
C17: Net Income Margin | H17: =H16/H11 -> 0.21349898 | I17: =I16/I11 -> 0.20387775 | J17: =J16/J11 -> 0.20815237 | K17: =K16/K11 -> 0.18052244 | L17: =L16/L11 -> 0.16922635 | M17: =M16/M11 -> 0.16610439 | N17: =N16/N11 -> 0.16259803 | O17: =O16/O11 -> 0.15531018
C20: CASH FLOW STATEMENT
C22: Operating | H22: =Model!F52 -> 15655.7 | I22: =Model!G52 -> 16011.851 | J22: =Model!H52 -> 17391.448 | K22: =Model!I52 -> 16527.626 | L22: =Model!J52 -> 16678.701 | M22: =Model!K52 -> 16854.717 | N22: =Model!L52 -> 17004.156 | O22: =Model!M52 -> 16909.283
C23: Investing | H23: =Model!F57 -> -9015 | I23: =Model!G57 -> -11733 | J23: =Model!H57 -> -11130 | K23: =Model!I57 -> -25475 | L23: =Model!J57 -> -7050 | M23: =Model!K57 -> -7275 | N23: =Model!L57 -> -7200 | O23: =Model!M57 -> -7687.5
C24: Financing | H24: =Model!F65 -> -3465 | I24: =Model!G65 -> -7761 | J24: =Model!H65 -> -7216 | K24: =Model!I65 -> 537.37491 | L24: =Model!J65 -> -9628.7008 | M24: =Model!K65 -> -9579.7168 | N24: =Model!L65 -> -9210.8535 | O24: =Model!M65 -> -6871.7098
C25: Change in Cash | H25: =SUM(H22:H24) -> 3175.7 | I25: =SUM(I22:I24) -> -3482.1494 | J25: =SUM(J22:J24) -> -954.5515 | K25: =SUM(K22:K24) -> -8409.9991 | L25: =SUM(L22:L24) -> 0 | M25: =SUM(M22:M24) -> 0 | N25: =SUM(N22:N24) -> 593.30282 | O25: =SUM(O22:O24) -> 2350.0732
C29: INCOME STATEMENT | J29: CASH FLOW STATEMENT

Sheet Inputs
B3: Drivers
B5: All figures in USD thousands unless stated | H5: =F52 -> 2023 | I5: =H5+1 -> 2024 | J5: =I5+1 -> 2025 | K5: =J5+1 -> 2026 | L5: =K5+1 -> 2027
E7: 2
C10: Sales Volume Growth | H10: {=INDEX(H12:H14,$E$7)} -> 0.02 | I10: {=INDEX(I12:I14,$E$7)} -> 0.01 | J10: {=INDEX(J12:J14,$E$7)} -> 0.01 | K10: {=INDEX(K12:K14,$E$7)} -> 0.005 | L10: {=INDEX(L12:L14,$E$7)} -> 0.005
C12: Best Case | H12: 0.03 | I12: 0.02 | J12: 0.02 | K12: 0.015 | L12: 0.015
C13: Base Case | H13: 0.02 | I13: 0.01 | J13: 0.01 | K13: 0.005 | L13: 0.005
C14: Worst Case | H14: 0.01 | I14: 0.01 | J14: 0.005 | K14: 0.005 | L14: 0.005
C17: Pricing Increases | H17: {=INDEX(H19:H21,$E$7)} -> 0.03 | I17: {=INDEX(I19:I21,$E$7)} -> 0.01 | J17: {=INDEX(J19:J21,$E$7)} -> 0.01 | K17: {=INDEX(K19:K21,$E$7)} -> 0.01 | L17: {=INDEX(L19:L21,$E$7)} -> 0.005
C19: Best Case | H19: 0.035 | I19: 0.02 | J19: 0.02 | K19: 0.02 | L19: 0.015
C20: Base Case | H20: 0.03 | I20: 0.01 | J20: 0.01 | K20: 0.01 | L20: 0.005
C21: Worst Case | H21: 0.01 | I21: 0.01 | J21: 0.005 | K21: 0.005 | L21: 0.005
C24: Capital Expenditure | H24: {=INDEX(H26:H28,$E$7)} -> 25475 | I24: {=INDEX(I26:I28,$E$7)} -> 7050 | J24: {=INDEX(J26:J28,$E$7)} -> 7275 | K24: {=INDEX(K26:K28,$E$7)} -> 7200 | L24: {=INDEX(L26:L28,$E$7)} -> 7687.5
C26: Best Case | H26: 23000 | I26: 6450 | J26: 6600 | K26: 6900 | L26: 7200
C27: Base Case | H27: 25475 | I27: 7050 | J27: 7275 | K27: 7200 | L27: 7687.5
C28: Worst Case | H28: 27500 | I28: 7800 | J28: 8100 | K28: 8250 | L28: 8400
B35: All figures in USD thousands unless stated | H35: =F52 -> 2023 | I35: =H35+1 -> 2024 | J35: =I35+1 -> 2025 | K35: =J35+1 -> 2026 | L35: =K35+1 -> 2027
C38: Working Capital
C39: Accounts Receivables | F39: (Days) | H39: 45 | I39: 45 | J39: 45 | K39: 45 | L39: 45
C40: Inventory | F40: (Days) | H40: 25 | I40: 25 | J40: 25 | K40: 25 | L40: 25
C41: Accounts Payable | F41: (Days) | H41: 40 | I41: 40 | J41: 40 | K41: 40 | L41: 40
C44: Other Annual Inputs
C45: Inflation Rate | H45: 0.035 | I45: 0.03 | J45: 0.03 | K45: 0.025 | L45: 0.025
C46: Term Debt | F46: Increase / (Decrease) | H46: -4000 | I46: -4000 | J46: -4000 | K46: -4000 | L46: -4000
C47: Common Equity | F47: Increase / (Decrease) | H47: -1000 | I47: -1000 | J47: -1000 | K47: -1000 | L47: -1000
C51: Dates | H51: Taxes
C52: First Year of Forecast | E52: (YYYY) | F52: 2023 | H52: Tax Rate | L52: 0.3
C53: Days in Period | F53: 365 | H53: First Year Tax Depreciation | L53: 0.5
H54: Blended Tax Depreciation Rate | L54: 0.15
H55: Tax Basis for Assets | K55: (End of 2022) | L55: 39211
C56: Other Single Inputs | H56: Tax Losses | K56: (End of 2022) | L56: 2657
C57: Plant Capacity | E57: (Units/Day) | F57: 1600
C58: Dividend Payout Ratio | F58: 0.2
C61: Interest Rates | H61: Depreciation
C62: Cash Balances | F62: 0.01 | H62: First Year Accounting Depreciation | L62: 0.5
C63: Revolving Credit Line | F63: 0.05 | H63: Useful Life: Existing Assets | K63: (Years) | L63: 16
C64: Long Term Debt | F64: 0.06 | H64: Useful Life: New Assets | K64: (Years) | L64: 20

Sheet Model
B3: Income Statement
B5: All figures in USD thousands unless stated | F5: =G5-1 -> 2020 | G5: =H5-1 -> 2021 | H5: =I5-1 -> 2022 | I5: =Inputs!F52 -> 2023 | J5: =I5+1 -> 2024 | K5: =J5+1 -> 2025 | L5: =K5+1 -> 2026 | M5: =L5+1 -> 2027
B6: {=CONCATENATE("Model Running : ",INDEX(Inputs!$C$12:$C$14,Inputs!$E$7 ), " Drivers")} -> Model Running : Base Case Drivers
B8: Inflation | F8: 0.024 | G8: 0.022 | H8: 0.023 | I8: =Inputs!H45 -> 0.035 | J8: =Inputs!I45 -> 0.03 | K8: =Inputs!J45 -> 0.03 | L8: =Inputs!K45 -> 0.025 | M8: =Inputs!L45 -> 0.025
B11: Revenue | F11: 50589 | G11: 51647.865 | H11: 53760.85 | I11: =I151 -> 56481.149 | J11: =J151 -> 57616.42 | K11: =K151 -> 58774.51 | L11: =L151 -> 59659.067 | M11: =M151 -> 60257.149
B12: COGS | F12: -24544.3 | G12: -25104.014 | H12: -25779.401 | I12: =-I197 -> -26798.044 | J12: =-J197 -> -27663.11 | K12: =-K197 -> -28556.593 | L12: =-L197 -> -29303.423 | M12: =-M197 -> -30069.915
B13: Gross Profit | F13: 26044.7 | G13: 26543.851 | H13: 27981.448 | I13: =SUM(I11:I12) -> 29683.105 | J13: =SUM(J11:J12) -> 29953.31 | K13: =SUM(K11:K12) -> 30217.918 | L13: =SUM(L11:L12) -> 30355.644 | M13: =SUM(M11:M12) -> 30187.234
B16: SG&A | F16: -5877 | G16: -6006 | H16: -6144 | I16: =H16*(1+I8) -> -6359.04 | J16: =I16*(1+J8) -> -6549.8112 | K16: =J16*(1+K8) -> -6746.3055 | L16: =K16*(1+L8) -> -6914.9632 | M16: =L16*(1+M8) -> -7087.8373
B17: Other | F17: -1764 | G17: -1931 | H17: -2026 | I17: =H17*(1+I8) -> -2096.91 | J17: =I17*(1+J8) -> -2159.8173 | K17: =J17*(1+K8) -> -2224.6118 | L17: =K17*(1+L8) -> -2280.2271 | M17: =L17*(1+M8) -> -2337.2328
B18: EBITDA | F18: 18403.7 | G18: 18606.851 | H18: 19811.448 | I18: =I13+SUM(I16:I17) -> 21227.155 | J18: =J13+SUM(J16:J17) -> 21243.681 | K18: =K13+SUM(K16:K17) -> 21247 | L18: =L13+SUM(L16:L17) -> 21160.454 | M18: =M13+SUM(M16:M17) -> 20762.164
B21: Depreciation | F21: -2960 | G21: -3196 | H21: -3452 | I21: =I271*-1 -> -5349.8125 | J21: =J271*-1 -> -6162.9375 | K21: =K271*-1 -> -6521.0625 | L21: =L271*-1 -> -6882.9375 | M21: =M271*-1 -> -7255.125
B22: EBIT | F22: 15443.7 | G22: 15410.851 | H22: 16359.449 | I22: =I18+I21 -> 15877.343 | J22: =J18+J21 -> 15080.744 | K22: =K18+K21 -> 14725.938 | L22: =L18+L21 -> 14277.516 | M22: =M18+M21 -> 13507.039
B25: Interest Expense | F25: -1688 | G25: -2200 | H25: -2350 | I25: =-I411 -> -1269.4149 | J25: =-J411 -> -1151.8635 | K25: =-K411 -> -779.21761 | L25: =-L411 -> -416.76911 | M25: =-M411 -> -120
B26: Interest Income | F26: 200 | G26: 180 | H26: 193 | I26: =I412*-1 -> 42.049996 | J26: =J412*-1 -> 0 | K26: =K412*-1 -> 0 | L26: =L412*-1 -> 2.9665141 | M26: =M412*-1 -> 17.683394
B27: EBT | F27: 13955.7 | G27: 13390.851 | H27: 14202.449 | I27: =I22+I25-I26 -> 14565.878 | J27: =J22+J25-J26 -> 13928.88 | K27: =K22+K25-K26 -> 13946.72 | L27: =L22+L25-L26 -> 13857.781 | M27: =M22+M25-M26 -> 13369.355
B30: Current Tax | F30: 0 | G30: 0 | H30: 0 | I30: =-I340 -> -2839.9247 | J30: =-J340 -> -3308.7027 | K30: =-K340 -> -3507.0061 | L30: =-L340 -> -3658.1985 | M30: =-M340 -> -3672.961
B31: Deferred Tax | F31: -3155 | G31: -2861 | H31: -3012 | I31: =-I341 -> -1529.8388 | J31: =-J341 -> -869.96137 | K31: =-K341 -> -677.00998 | L31: =-L341 -> -499.13567 | M31: =-M341 -> -337.84563
B32: Total Tax | F32: -3155 | G32: -2861 | H32: -3012 | I32: =SUM(I30:I31) -> -4369.7634 | J32: =SUM(J30:J31) -> -4178.6641 | K32: =SUM(K30:K31) -> -4184.016 | L32: =SUM(L30:L31) -> -4157.3342 | M32: =SUM(M30:M31) -> -4010.8066
B35: Net Income | F35: 10800.7 | G35: 10529.851 | H35: 11190.449 | I35: =I27+I32 -> 10196.115 | J35: =J27+J32 -> 9750.2162 | K35: =K27+K32 -> 9762.7041 | L35: =L27+L32 -> 9700.4464 | M35: =M27+M32 -> 9358.5488
B39: Cash Flow Statement
B41: All figures in USD thousands unless stated | F41: =F5 -> 2020 | G41: =G5 -> 2021 | H41: =H5 -> 2022 | I41: =I5 -> 2023 | J41: =J5 -> 2024 | K41: =K5 -> 2025 | L41: =L5 -> 2026 | M41: =M5 -> 2027
B42: =B6 -> Model Running : Base Case Drivers
B45: CASH FROM OPERATING
B46: Net Income | F46: 10800.7 | G46: 10529.851 | H46: 11190.449 | I46: =I35 -> 10196.115 | J46: =J35 -> 9750.2162 | K46: =K35 -> 9762.7041 | L46: =L35 -> 9700.4464 | M46: =M35 -> 9358.5488
B47: Deferred Taxes | F47: 3155 | G47: 2861 | H47: 3012 | I47: =I31*-1 -> 1529.8388 | J47: =J31*-1 -> 869.96137 | K47: =K31*-1 -> 677.00998 | L47: =L31*-1 -> 499.13567 | M47: =M31*-1 -> 337.84563
B48: Depreciation | F48: 2960 | G48: 3196 | H48: 3452 | I48: =I21*-1 -> 5349.8125 | J48: =J21*-1 -> 6162.9375 | K48: =K21*-1 -> 6521.0625 | L48: =L21*-1 -> 6882.9375 | M48: =M21*-1 -> 7255.125
B49: Cash From Accounts Receivable | F49: -600 | G49: -625 | H49: -291 | I49: =I226 -> -339.42933 | J49: =J226 -> -139.96493 | K49: =K226 -> -142.77822 | L49: =L226 -> -109.0549 | M49: =M226 -> -73.736154
B50: Cash From Inventory | F50: -400 | G50: -131 | H50: -86 | I50: =I227 -> 173.51756 | J50: =J227 -> -59.25115 | K50: =K227 -> -61.197408 | L50: =L227 -> -51.152739 | M50: =M227 -> -52.499473
B51: Cash From Accounts Payable | F51: -260 | G51: 181 | H51: 114 | I51: =I228 -> -382.2281 | J51: =J228 -> 94.801841 | K51: =K228 -> 97.915853 | L51: =L228 -> 81.844382 | M51: =M228 -> 83.999157
B52: Subtotal | F52: 15655.7 | G52: 16011.851 | H52: 17391.448 | I52: =SUM(I46:I51) -> 16527.626 | J52: =SUM(J46:J51) -> 16678.701 | K52: =SUM(K46:K51) -> 16854.717 | L52: =SUM(L46:L51) -> 17004.156 | M52: =SUM(M46:M51) -> 16909.283
B55: CASH FROM INVESTING
B56: Capital Expenditure | F56: -9015 | G56: -11733 | H56: -11130 | I56: =I284*-1 -> -25475 | J56: =J284*-1 -> -7050 | K56: =K284*-1 -> -7275 | L56: =L284*-1 -> -7200 | M56: =M284*-1 -> -7687.5
B57: Subtotal | F57: -9015 | G57: -11733 | H57: -11130 | I57: =SUM(I56) -> -25475 | J57: =SUM(J56) -> -7050 | K57: =SUM(K56) -> -7275 | L57: =SUM(L56) -> -7200 | M57: =SUM(M56) -> -7687.5
B60: CASH FROM FINANCING
B61: Change in Long-Term Debt | F61: 0 | G61: -4000 | H61: -4000 | I61: =I371 -> -4000 | J61: =J371 -> -4000 | K61: =K371 -> -4000 | L61: =L371 -> -4000 | M61: =M371 -> -4000
B62: Change in Revolving Credit Line | F62: 0 | G62: 0 | H62: 0 | I62: =I403 -> 7576.5978 | J62: =J403 -> -2678.6576 | K62: =K403 -> -2627.176 | L62: =L403 -> -2270.7642 | M62: =M403 -> 0
B63: Change in Common Equity | F63: 0 | G63: 0 | H63: 0 | I63: =I428 -> -1000 | J63: =J428 -> -1000 | K63: =K428 -> -1000 | L63: =L428 -> -1000 | M63: =M428 -> -1000
B64: Dividends | F64: -3465 | G64: -3761 | H64: -3216 | I64: =I442 -> -2039.2229 | J64: =J442 -> -1950.0432 | K64: =K442 -> -1952.5408 | L64: =L442 -> -1940.0893 | M64: =M442 -> -1871.7098
B65: Subtotal | F65: -3465 | G65: -7761 | H65: -7216 | I65: =SUM(I61:I64) -> 537.37491 | J65: =SUM(J61:J64) -> -9628.7008 | K65: =SUM(K61:K64) -> -9579.7168 | L65: =SUM(L61:L64) -> -9210.8535 | M65: =SUM(M61:M64) -> -6871.7098
B68: CASH BALANCE
B69: Beginning of the Year | F69: 9671 | G69: 12846.7 | H69: 9364.5506 | I69: =H71 -> 8409.9991 | J69: =I71 -> 0 | K69: =J71 -> 0 | L69: =K71 -> 0 | M69: =L71 -> 593.30282
B70: Increase / (Decrease) | F70: 3175.7 | G70: -3482.1494 | H70: -954.5515 | I70: =I52+I57+I65 -> -8409.9991 | J70: =J52+J57+J65 -> 0 | K70: =K52+K57+K65 -> 0 | L70: =L52+L57+L65 -> 593.30282 | M70: =M52+M57+M65 -> 2350.0732
B71: End of the Year | F71: 12846.7 | G71: 9364.5506 | H71: 8409.9991 | I71: =SUM(I69:I70) -> 0 | J71: =SUM(J69:J70) -> 0 | K71: =SUM(K69:K70) -> 0 | L71: =SUM(L69:L70) -> 593.30282 | M71: =SUM(M69:M70) -> 2943.376
B75: Balance Sheet
B77: All figures in USD thousands unless stated | F77: =F5 -> 2020 | G77: =G5 -> 2021 | H77: =H5 -> 2022 | I77: =I5 -> 2023 | J77: =J5 -> 2024 | K77: =K5 -> 2025 | L77: =L5 -> 2026 | M77: =M5 -> 2027
B78: =B6 -> Model Running : Base Case Drivers
B80: ASSETS
B82: Cash | F82: 12846.7 | G82: 9364.5506 | H82: 8409.9991 | I82: =I71 -> 0 | J82: =J71 -> 0 | K82: =K71 -> 0 | L82: =L71 -> 593.30282 | M82: =M71 -> 2943.376
B83: Accounts Receivable | F83: 5708 | G83: 6333 | H83: 6624 | I83: =I218 -> 6963.4293 | J83: =J218 -> 7103.3943 | K83: =K218 -> 7246.1725 | L83: =L218 -> 7355.2274 | M83: =M218 -> 7428.9635
B84: Inventories | F84: 1792 | G84: 1923 | H84: 2009 | I84: =I219 -> 1835.4824 | J84: =J219 -> 1894.7336 | K84: =K219 -> 1955.931 | L84: =L219 -> 2007.0837 | M84: =M219 -> 2059.5832
B85: Total Current Assets | F85: 20346.7 | G85: 17620.551 | H85: 17042.999 | I85: =SUM(I82:I84) -> 8798.9118 | J85: =SUM(J82:J84) -> 8998.1278 | K85: =SUM(K82:K84) -> 9202.1035 | L85: =SUM(L82:L84) -> 9955.6139 | M85: =SUM(M82:M84) -> 12431.923
B87: Property Plant & Equipment | F87: 59192 | G87: 67729 | H87: 75407 | I87: =I294 -> 95532.188 | J87: =J294 -> 96419.25 | K87: =K294 -> 97173.188 | L87: =L294 -> 97490.25 | M87: =M294 -> 97922.625
B90: Total Assets | F90: 79538.7 | G90: 85349.551 | H90: 92449.999 | I90: =I85+I87 -> 104331.1 | J90: =J85+J87 -> 105417.38 | K90: =K85+K87 -> 106375.29 | L90: =L85+L87 -> 107445.86 | M90: =M85+M87 -> 110354.55
B93: LIABILITIES
B95: Accounts Payable | F95: 3024 | G95: 3205 | H95: 3319 | I95: =I220 -> 2936.7719 | J95: =J220 -> 3031.5737 | K95: =K220 -> 3129.4896 | L95: =L220 -> 3211.334 | M95: =M220 -> 3295.3331
B96: Revolving Credit Line | F96: 0 | G96: 0 | H96: 0 | I96: =I404 -> 7576.5978 | J96: =J404 -> 4897.9402 | K96: =K404 -> 2270.7642 | L96: =L404 -> 0 | M96: =M404 -> 0
B97: Total Current Liabilities | F97: 3024 | G97: 3205 | H97: 3319 | I97: =SUM(I95:I96) -> 10513.37 | J97: =SUM(J95:J96) -> 7929.514 | K97: =SUM(K95:K96) -> 5400.2538 | L97: =SUM(L95:L96) -> 3211.334 | M97: =SUM(M95:M96) -> 3295.3331
B99: Deferred Taxes | F99: 4155 | G99: 7016 | H99: 10028 | I99: =H99+I47 -> 11557.839 | J99: =I99+J47 -> 12427.8 | K99: =J99+K47 -> 13104.81 | L99: =K99+L47 -> 13603.946 | M99: =L99+M47 -> 13941.791
B100: Long-Term Debt | F100: 28000 | G100: 24000 | H100: 20000 | I100: =I372 -> 16000 | J100: =J372 -> 12000 | K100: =K372 -> 8000 | L100: =L372 -> 4000 | M100: =M372 -> 0
B101: Total Liabilities | F101: 35179 | G101: 34221 | H101: 33347 | I101: =SUM(I97,I99,I100) -> 38071.208 | J101: =SUM(J97,J99,J100) -> 32357.314 | K101: =SUM(K97,K99,K100) -> 26505.064 | L101: =SUM(L97,L99,L100) -> 20815.28 | M101: =SUM(M97,M99,M100) -> 17237.125
B104: EQUITY
B106: Common Equity | F106: 38669.7 | G106: 38669.7 | H106: 38669.7 | I106: =I429 -> 37669.7 | J106: =J429 -> 36669.7 | K106: =K429 -> 35669.7 | L106: =L429 -> 34669.7 | M106: =M429 -> 33669.7
B107: Retained Earnings | F107: 5690 | G107: 12458.851 | H107: 20433.299 | I107: =I443 -> 28590.191 | J107: =J443 -> 36390.364 | K107: =K443 -> 44200.527 | L107: =L443 -> 51960.884 | M107: =M443 -> 59447.723
B108: Total Shareholders' Equity | F108: 44359.7 | G108: 51128.551 | H108: 59102.999 | I108: =SUM(I106:I107) -> 66259.891 | J108: =SUM(J106:J107) -> 73060.064 | K108: =SUM(K106:K107) -> 79870.227 | L108: =SUM(L106:L107) -> 86630.584 | M108: =SUM(M106:M107) -> 93117.423
B111: Total Liabilities & Equity | F111: 79538.7 | G111: 85349.551 | H111: 92449.999 | I111: =I101+I108 -> 104331.1 | J111: =J101+J108 -> 105417.38 | K111: =K101+K108 -> 106375.29 | L111: =L101+L108 -> 107445.86 | M111: =M101+M108 -> 110354.55
B114: Check | F114: =ROUND(F90-F111,0) -> 0 | G114: =ROUND(G90-G111,0) -> 0 | H114: =ROUND(H90-H111,0) -> 0 | I114: =ROUND(I90-I111,0) -> 0 | J114: =ROUND(J90-J111,0) -> 0 | K114: =ROUND(K90-K111,0) -> 0 | L114: =ROUND(L90-L111,0) -> 0 | M114: =ROUND(M90-M111,0) -> 0
B118: Revenue Schedule
B120: All figures in USD thousands unless stated | F120: =F5 -> 2020 | G120: =G5 -> 2021 | H120: =H5 -> 2022 | I120: =I5 -> 2023 | J120: =J5 -> 2024 | K120: =K5 -> 2025 | L120: =L5 -> 2026 | M120: =M5 -> 2027
B121: =B6 -> Model Running : Base Case Drivers
B124: OPERATIONS
B126: Sales Volume Growth | G126: =G128/F128-1 -> 0.00071428571 | H126: 0.0206995 | I126: =Inputs!H10 -> 0.02 | J126: =Inputs!I10 -> 0.01 | K126: =Inputs!J10 -> 0.01 | L126: =Inputs!K10 -> 0.005 | M126: =Inputs!L10 -> 0.005
B128: Sales Volume | D128: (Units/Day) | F128: 1400 | G128: 1401 | H128: 1430 | I128: =H128*(1+I126) -> 1458.6 | J128: =I128*(1+J126) -> 1473.186 | K128: =J128*(1+K126) -> 1487.9179 | L128: =K128*(1+L126) -> 1495.3574 | M128: =L128*(1+M126) -> 1502.8342
B129: Plant Capacity | D129: (Units/Day) | F129: 1500 | G129: 1500 | H129: 1500 | I129: =Inputs!$F$57 -> 1600 | J129: =Inputs!$F$57 -> 1600 | K129: =Inputs!$F$57 -> 1600 | L129: =Inputs!$F$57 -> 1600 | M129: =Inputs!$F$57 -> 1600
B130: Operational Efficiency | F130: =F128/F129 -> 0.93333333 | G130: =G128/G129 -> 0.934 | H130: =H128/H129 -> 0.95333333 | I130: =I128/I129 -> 0.911625 | J130: =J128/J129 -> 0.92074125 | K130: =K128/K129 -> 0.92994866 | L130: =L128/L129 -> 0.93459841 | M130: =M128/M129 -> 0.9392714
B134: VOLUME
B136: Days in Period | F136: 365 | G136: 365 | H136: 365 | I136: =Inputs!$F$53 -> 365 | J136: =Inputs!$F$53 -> 365 | K136: =Inputs!$F$53 -> 365 | L136: =Inputs!$F$53 -> 365 | M136: =Inputs!$F$53 -> 365
B137: Sales Volume | D137: (Units/Day) | F137: =F128 -> 1400 | G137: =G128 -> 1401 | H137: =H128 -> 1430 | I137: =I128 -> 1458.6 | J137: =J128 -> 1473.186 | K137: =K128 -> 1487.9179 | L137: =L128 -> 1495.3574 | M137: =M128 -> 1502.8342
B138: Sales Volume | D138: (Units) | F138: =F137*F136 -> 511000 | G138: =G137*G136 -> 511365 | H138: =H137*H136 -> 521950 | I138: =I137*I136 -> 532389 | J138: =J137*J136 -> 537712.89 | K138: =K137*K136 -> 543090.02 | L138: =L137*L136 -> 545805.47 | M138: =M137*M136 -> 548534.5
B141: PRICING
B143: Pricing Increases | G143: =G144/F144-1 -> 0.02020202 | H143: =H144/G144-1 -> 0.01980198 | I143: =Inputs!H17 -> 0.03 | J143: =Inputs!I17 -> 0.01 | K143: =Inputs!J17 -> 0.01 | L143: =Inputs!K17 -> 0.01 | M143: =Inputs!L17 -> 0.005
B144: Unit Price | D144: (USD/Unit) | F144: 99 | G144: 101 | H144: 103 | I144: =H144*(1+I143) -> 106.09 | J144: =I144*(1+J143) -> 107.1509 | K144: =J144*(1+K143) -> 108.22241 | L144: =K144*(1+L143) -> 109.30463 | M144: =L144*(1+M143) -> 109.85116
B147: REVENUE
B149: Sales Volume | D149: (Units) | F149: =F138 -> 511000 | G149: 511365 | H149: 521950 | I149: =I138 -> 532389 | J149: =J138 -> 537712.89 | K149: =K138 -> 543090.02 | L149: =L138 -> 545805.47 | M149: =M138 -> 548534.5
B150: Sales Price | D150: (USD/Unit) | F150: =F144 -> 99 | G150: 101 | H150: 103 | I150: =I144 -> 106.09 | J150: =J144 -> 107.1509 | K150: =K144 -> 108.22241 | L150: =L144 -> 109.30463 | M150: =M144 -> 109.85116
B151: Revenue | F151: =F149*F150/1000 -> 50589 | G151: =G149*G150/1000 -> 51647.865 | H151: =H149*H150/1000 -> 53760.85 | I151: =I149*I150/1000 -> 56481.149 | J151: =J149*J150/1000 -> 57616.42 | K151: =K149*K150/1000 -> 58774.51 | L151: =L149*L150/1000 -> 59659.067 | M151: =M149*M150/1000 -> 60257.149
B155: Operational Capacity Exceeded? | F155: =IF(F130>=1,1,0) -> 0 | G155: =IF(G130>=1,1,0) -> 0 | H155: =IF(H130>=1,1,0) -> 0 | I155: =IF(I130>=1,1,0) -> 0 | J155: =IF(J130>=1,1,0) -> 0 | K155: =IF(K130>=1,1,0) -> 0 | L155: =IF(L130>=1,1,0) -> 0 | M155: =IF(M130>=1,1,0) -> 0
B159: Cost Schedule
B161: All figures in USD thousands unless stated | F161: =F5 -> 2020 | G161: =G5 -> 2021 | H161: =H5 -> 2022 | I161: =I5 -> 2023 | J161: =J5 -> 2024 | K161: =K5 -> 2025 | L161: =L5 -> 2026 | M161: =M5 -> 2027
B162: =B6 -> Model Running : Base Case Drivers
B164: Sales Volume | F164: =F149 -> 511000 | G164: =G149 -> 511365 | H164: =H149 -> 521950 | I164: =I149 -> 532389 | J164: =J149 -> 537712.89 | K164: =K149 -> 543090.02 | L164: =L149 -> 545805.47 | M164: =M149 -> 548534.5
B165: Inflation | F165: =F8 -> 0.024 | G165: =G8 -> 0.022 | H165: =H8 -> 0.023 | I165: =I8 -> 0.035 | J165: =J8 -> 0.03 | K165: =K8 -> 0.03 | L165: =L8 -> 0.025 | M165: =M8 -> 0.025
B167: VARIABLE COSTS
B169: Materials | D169: (USD/Unit) | F169: 9.5 | G169: 9.72 | H169: 9.91 | I169: =H169*(1+I$165) -> 10.25685 | J169: =I169*(1+J$165) -> 10.564556 | K169: =J169*(1+K$165) -> 10.881492 | L169: =K169*(1+L$165) -> 11.153529 | M169: =L169*(1+M$165) -> 11.432368
B170: Packaging | D170: (USD/Unit) | F170: 0.8 | G170: 0.84 | H170: 0.86 | I170: =H170*(1+I$165) -> 0.8901 | J170: =I170*(1+J$165) -> 0.916803 | K170: =J170*(1+K$165) -> 0.94430709 | L170: =K170*(1+L$165) -> 0.96791477 | M170: =L170*(1+M$165) -> 0.99211264
B171: Subtotal | F171: 10.3 | G171: 10.56 | H171: 10.77 | I171: =SUM(I169:I170) -> 11.14695 | J171: =SUM(J169:J170) -> 11.481359 | K171: =SUM(K169:K170) -> 11.825799 | L171: =SUM(L169:L170) -> 12.121444 | M171: =SUM(M169:M170) -> 12.42448
B173: Materials | F173: =F169*F164/1000 -> 4854.5 | G173: =G169*G164/1000 -> 4970.4678 | H173: =H169*H164/1000 -> 5172.5245 | I173: =I169*I164/1000 -> 5460.6341 | J173: =J169*J164/1000 -> 5680.6977 | K173: =K169*K164/1000 -> 5909.6298 | L173: =L169*L164/1000 -> 6087.6574 | M173: =M169*M164/1000 -> 6271.0481
B174: Packaging | F174: =F164*F170/1000 -> 408.8 | G174: =G164*G170/1000 -> 429.5466 | H174: =H164*H170/1000 -> 448.877 | I174: =I164*I170/1000 -> 473.87945 | J174: =J164*J170/1000 -> 492.97679 | K174: =K164*K170/1000 -> 512.84376 | L174: =L164*L170/1000 -> 528.29317 | M174: =M164*M170/1000 -> 544.20801
B175: Subtotal | F175: =SUM(F173:F174) -> 5263.3 | G175: =SUM(G173:G174) -> 5400.0144 | H175: =SUM(H173:H174) -> 5621.4015 | I175: =SUM(I173:I174) -> 5934.5136 | J175: =SUM(J173:J174) -> 6173.6745 | K175: =SUM(K173:K174) -> 6422.4735 | L175: =SUM(L173:L174) -> 6615.9506 | M175: =SUM(M173:M174) -> 6815.2561
B178: FIXED COSTS
B180: Labor | D180: (USD/Unit) | F180: =F184/F164*1000 -> 30.587084 | G180: =G184/G164*1000 -> 31.236006 | H180: =H184/H164*1000 -> 31.307597 | I180: =I184/I164*1000 -> 31.768002 | J180: =J184/J164*1000 -> 32.397072 | K180: =K184/K164*1000 -> 33.038598 | L180: =L184/L164*1000 -> 33.696082 | M180: =M184/M164*1000 -> 34.366651
...
